be_great/__init__.py
be_great/great.py
be_great/great_dataset.py
be_great/great_start.py
be_great/great_trainer.py
be_great/great_utils.py
be_great-0.0.9.dist-info/licenses/LICENSE
be_great-0.0.9.dist-info/METADATA
be_great-0.0.9.dist-info/WHEEL
be_great-0.0.9.dist-info/top_level.txt
be_great-0.0.9.dist-info/RECORD
