Metadata-Version: 2.4
Name: be_great
Version: 0.0.9
Summary: Generating Realistic Tabular Data using Large Language Models
Author-email: Kathrin Sessler <kathrin.sessler@tum.de>, Vadim Borisov <vadim@tabularis.ai>
License: MIT License
Project-URL: Homepage, https://github.com/tabularis-ai/be_great
Project-URL: Documentation, https://tabularis-ai.github.io/be_great/
Keywords: great,pytorch,tabular data,data generation,transformer,language models,deep learning
Classifier: Programming Language :: Python :: 3
Classifier: License :: OSI Approved :: MIT License
Classifier: Operating System :: OS Independent
Requires-Python: >=3.9
License-File: LICENSE
Requires-Dist: datasets>=2.5.2
Requires-Dist: numpy>=1.23.1
Requires-Dist: pandas>=1.4.4
Requires-Dist: scikit_learn>=1.1.1
Requires-Dist: torch>=1.10.2
Requires-Dist: tqdm>=4.64.1
Requires-Dist: transformers>=4.22.1
Requires-Dist: accelerate>=0.20.1
Dynamic: license-file
